{
  "type": "Feature",
  "properties": {
    "date:inception_lower": "2024-06-17",
    "date:inception_upper": "2024-06-17",
    "flysfo:gate_code": "B11",
    "iso:country": "US",
    "millsfield:wayfinding_detail": "B",
    "millsfield:wayfinding_kind": "HMT1",
    "sfo:level": 2,
    "sfomuseum:is_sfo": 1,
    "sfomuseum:name": "B11",
    "sfomuseum:placetype": "gate",
    "sfomuseum:post_security": 1,
    "wof:label": "B11 (2024-06-17)",
    "wof:name": "B11",
    "wof:placetype": "venue",
    "wof:placetype_alt": [
      "gate"
    ]
  },
  "geometry": {"coordinates":[-122.3852563710993,37.61268084197204],"type":"Point"}
}
