{
  "type": "Feature",
  "properties": {
    "date:inception_lower":"2017-01-01",
    "date:inception_upper":"2017-12-31",
    "iso:country":"US",
    "sfomuseum:is_sfo":1,
    "sfomuseum:placetype":"gate",
    "sfomuseum:post_security":1,
    "wof:name":"D50B",
    "wof:placetype":"venue"
},
  "geometry": {"coordinates":[-122.38224640222789,37.61690229561979],"type":"Point"}
}