{
  "type": "Feature",
  "properties": {
    "date:inception_lower":"2019-07-23",
    "date:inception_upper":"2019-07-23",
    "iso:country":"US",
    "sfomuseum:is_sfo":1,
    "sfomuseum:placetype":"gate",
    "sfomuseum:post_security":1,
    "wof:label":"B18 (2019)",
    "wof:name":"B18",
    "wof:placetype":"venue",
    "wof:placetype_alt":[
        "gate"
    ]
},
  "geometry": {"coordinates":[-122.385389,37.611265],"type":"Point"}
}