{
  "type": "Feature",
  "properties": {
    "date:inception_lower":"2017-01-01",
    "date:inception_upper":"2017-12-31",
    "flysfo:gate_code":"68",
    "iso:country":"US",
    "sfomuseum:is_sfo":1,
    "sfomuseum:placetype":"gate",
    "sfomuseum:post_security":1,
    "wof:name":"E68",
    "wof:placetype":"venue",
    "wof:placetype_alt":"gate"
},
  "geometry": {"coordinates":[-122.38449621099994,37.61919747600007],"type":"Point"}
}