{
  "type": "Feature",
  "properties": {
    "date:inception_lower": "2021-11-09",
    "date:inception_upper": "2021-11-09",
    "flysfo:gate_code": "C10",
    "iso:country": "US",
    "millsfield:wayfinding_detail": "C",
    "millsfield:wayfinding_kind": "T1",
    "sfo:level": 2,
    "sfomuseum:is_sfo": 1,
    "sfomuseum:name": "C10",
    "sfomuseum:placetype": "gate",
    "sfomuseum:post_security": 1,
    "wof:label": "C10 (2021-11-09)",
    "wof:name": "C10",
    "wof:placetype": "venue",
    "wof:placetype_alt": [
      "gate"
    ]
  },
  "geometry": {"coordinates":[-122.38227626090816,37.614649472380854],"type":"Point"}
}
