{
  "type": "Feature",
  "properties": {
    "date:inception_lower": "2024-11-05",
    "date:inception_upper": "2024-11-05",
    "flysfo:gate_code": "B21",
    "iso:country": "US",
    "millsfield:wayfinding_detail": "B",
    "millsfield:wayfinding_kind": "HMT1",
    "sfo:level": 2,
    "sfomuseum:is_sfo": 1,
    "sfomuseum:name": "B21",
    "sfomuseum:placetype": "gate",
    "sfomuseum:post_security": 1,
    "wfnd:detail": "HMT1",
    "wfnd:is_restricted": true,
    "wfnd:kind": "HMT1",
    "wfnd:level": 2,
    "wfnd:placetype": "gate",
    "wof:label": "B21 (2024-11-05)",
    "wof:name": "B21",
    "wof:placetype": "venue",
    "wof:placetype_alt": [
      "gate"
    ]
  },
  "geometry": {"coordinates":[-122.38580386207994,37.61065119375434],"type":"Point"}
}
