{
  "type": "Feature",
  "properties": {
    "date:inception_lower": "2021-05-25",
    "date:inception_upper": "2021-05-25",
    "flysfo:gate_code": "A6S",
    "iso:country": "US",
    "millsfield:wayfinding_detail": "A",
    "millsfield:wayfinding_kind": "ITB",
    "sfo:level": 0,
    "sfomuseum:is_sfo": 1,
    "sfomuseum:name": "A6S",
    "sfomuseum:placetype": "gate",
    "sfomuseum:post_security": 1,
    "wof:label": "A6S (2021-05-25)",
    "wof:name": "A6S",
    "wof:placetype": "venue",
    "wof:placetype_alt": "gate"
  },
  "geometry": {"coordinates":[-122.38881644491168,37.61298469497198],"type":"Point"}
}
