{
  "type": "Feature",
  "properties": {
    "date:inception_lower": "2021-05-25",
    "date:inception_upper": "2021-05-25",
    "flysfo:gate_code": "G105",
    "iso:country": "US",
    "millsfield:wayfinding_detail": "G",
    "millsfield:wayfinding_kind": "ITB",
    "sfo:level": 0,
    "sfomuseum:is_sfo": 1,
    "sfomuseum:name": "G105",
    "sfomuseum:placetype": "gate",
    "sfomuseum:post_security": 1,
    "wfnd:placetype": "gate",
    "wof:label": "G105 (2021-05-25)",
    "wof:name": "G105",
    "wof:placetype": "venue",
    "wof:placetype_alt": [
      "gate"
    ]
  },
  "geometry": {"coordinates":[-122.39306958336458,37.616545621747285],"type":"Point"}
}
