{
  "type": "Feature",
  "properties": {
    "date:inception_lower": "2024-06-17",
    "date:inception_upper": "2024-06-17",
    "iso:country": "US",
    "sfo:level": 2,
    "sfomuseum:is_sfo": 1,
    "sfomuseum:name": "Security Checkpoint G",
    "sfomuseum:placetype": "checkpoint",
    "sfomuseum:post_security": 0,
    "wof:label": "Security Checkpoint G (2024-06-17)",
    "wof:name": "Security Checkpoint G",
    "wof:placetype": "venue",
    "wof:placetype_alt": [
      "checkpoint"
    ]
  },
  "geometry": {"coordinates":[-122.38970083272108,37.61676646474914],"type":"Point"}
}
