{
  "type": "Feature",
  "properties": {
    "date:inception_lower": "2024-11-05",
    "date:inception_upper": "2024-11-05",
    "flysfo:gate_code": "G11",
    "iso:country": "US",
    "millsfield:wayfinding_detail": "G",
    "millsfield:wayfinding_kind": "ITB",
    "sfo:level": 2,
    "sfomuseum:is_sfo": 1,
    "sfomuseum:name": "G11",
    "sfomuseum:placetype": "gate",
    "sfomuseum:post_security": 1,
    "wfnd:detail": "ITB",
    "wfnd:is_restricted": true,
    "wfnd:kind": "ITB",
    "wfnd:level": 2,
    "wfnd:placetype": "gate",
    "wof:label": "G11 (2024-11-05)",
    "wof:name": "G11",
    "wof:placetype": "venue",
    "wof:placetype_alt": [
      "gate"
    ]
  },
  "geometry": {"coordinates":[-122.39341563178623,37.61851220158672],"type":"Point"}
}
