{
  "type": "Feature",
  "properties": {
    "date:inception_lower":"2019-07-23",
    "date:inception_upper":"2019-07-23",
    "flysfo:gate_code":"65",
    "iso:country":"US",
    "sfomuseum:is_sfo":1,
    "sfomuseum:placetype":"gate",
    "sfomuseum:post_security":1,
    "wof:name":"E65 (2019-07-23)",
    "wof:placetype":"venue",
    "wof:placetype_alt":[
        "gate"
    ]
},
  "geometry": {"coordinates":[-122.38402780499996,37.61942459700003],"type":"Point"}
}