{
  "type": "Feature",
  "properties": {
    "date:inception_lower":"2019-07-23",
    "date:inception_upper":"2019-07-23",
    "flysfo:gate_code":"A9",
    "iso:country":"US",
    "sfomuseum:is_sfo":1,
    "sfomuseum:placetype":"gate",
    "sfomuseum:post_security":1,
    "wof:label":"A9 (2019)",
    "wof:name":"A9",
    "wof:placetype":"venue",
    "wof:placetype_alt":[
        "gate"
    ]
},
  "geometry": {"coordinates":[-122.38991190399997,37.61156489300004],"type":"Point"}
}