{
  "type": "Feature",
  "properties": {
    "date:inception_lower": "2021-11-09",
    "date:inception_upper": "2021-11-09",
    "flysfo:gate_code": "B8",
    "iso:country": "US",
    "sfo:level": 2,
    "sfomuseum:is_sfo": 1,
    "sfomuseum:name": "B8",
    "sfomuseum:placetype": "gate",
    "sfomuseum:post_security": 1,
    "wof:label": "B8 (2021-11-09)",
    "wof:name": "B8",
    "wof:placetype": "venue",
    "wof:placetype_alt": [
      "gate"
    ]
  },
  "geometry": {"coordinates":[-122.3842265731441,37.61308745148253],"type":"Point"}
}
