{
  "type": "Feature",
  "properties": {
    "date:inception_lower": "2021-05-25",
    "date:inception_upper": "2021-05-25",
    "flysfo:gate_code": "G13R",
    "iso:country": "US",
    "millsfield:wayfinding_detail": "G",
    "millsfield:wayfinding_kind": "ITB",
    "sfo:level": 0,
    "sfomuseum:is_sfo": 1,
    "sfomuseum:name": "G13R",
    "sfomuseum:placetype": "gate",
    "sfomuseum:post_security": 1,
    "wof:label": "G13R (2021-05-25)",
    "wof:name": "G13R",
    "wof:placetype": "venue",
    "wof:placetype_alt": "gate"
  },
  "geometry": {"coordinates":[-122.39387136224208,37.61874598116525],"type":"Point"}
}
