{
  "type": "Feature",
  "properties": {
    "date:inception_lower": "2024-11-05",
    "date:inception_upper": "2024-11-05",
    "flysfo:gate_code": "A1",
    "iso:country": "US",
    "millsfield:wayfinding_detail": "A",
    "millsfield:wayfinding_kind": "ITB",
    "sfo:level": 2,
    "sfomuseum:is_sfo": 1,
    "sfomuseum:name": "A1",
    "sfomuseum:placetype": "gate",
    "sfomuseum:post_security": 1,
    "wfnd:detail": "A",
    "wfnd:is_restricted": true,
    "wfnd:kind": "ITB",
    "wfnd:level": 2,
    "wfnd:placetype": "gate",
    "wof:label": "A1 (2024-11-05)",
    "wof:name": "A1",
    "wof:placetype": "venue",
    "wof:placetype_alt": [
      "gate"
    ]
  },
  "geometry": {"coordinates":[-122.38835508936441,37.61389686136704],"type":"Point"}
}
