{
  "type": "Feature",
  "properties": {
    "date:inception_lower": "2024-06-17",
    "date:inception_upper": "2024-06-17",
    "flysfo:gate_code": "A6",
    "iso:country": "US",
    "millsfield:wayfinding_detail": "A",
    "millsfield:wayfinding_kind": "ITB",
    "sfo:level": 2,
    "sfomuseum:is_sfo": 1,
    "sfomuseum:name": "A6",
    "sfomuseum:placetype": "gate",
    "sfomuseum:post_security": 1,
    "wof:label": "A6 (2024-06-17)",
    "wof:name": "A6",
    "wof:placetype": "venue",
    "wof:placetype_alt": [
      "gate"
    ]
  },
  "geometry": {"coordinates":[-122.38923509142415,37.61264677192996],"type":"Point"}
}
